{
  "lists": [
    "Ideas",
    "Bugs",
    "Client feedback",
    "Feature requests",
    "In progress",
    "In review",
    "Friendly Beta 0.1",
    "Live Beta 0.2",
    "Live 1.0"
  ],
  "labels": {
    "Wave 1": "red",
    "Wave 2": "orange",
    "Tier A": "yellow",
    "DTE/SII": "green",
    "Design System": "purple",
    "Core": "blue",
    "Roadmap": "sky",
    "Bug": "pink",
    "Blocked": "black"
  },
  "cards": [
    {
      "list": "In progress",
      "name": "[Onboarding] Import Facturas / Boletas históricas (registro, sin SII)",
      "labels": [
        "Core"
      ],
      "desc": "DTEs ya emitidos en plataforma anterior. Solo registro para histórico de cliente y cobranza — NO se reemiten al SII, no consumen folio CAF, no generan PDF nuevo. Marca origen=externo.",
      "checklist": [
        "UI dentro de pestaña 'Migración inicial' (solo admin)",
        "Plantilla .xlsx descargable con columnas documentadas",
        "Backend: parser xlsx con validación de columnas/tipos",
        "Validación previa con preview + conteo de filas válidas/inválidas",
        "Import transaccional por lote: rollback si fatal, reporte fila a fila si recuperable",
        "Reporte descargable post-import (creado / actualizado / pendiente / error + motivo)",
        "Idempotente: re-correr el mismo Excel no duplica",
        "--- Específico ---",
        "Hojas: Cabecera DTE / Detalle DTE",
        "Cabecera: tipo_dte, folio, rut_receptor, fecha_emision, neto, iva, total, estado_pago",
        "Detalle: folio, sku, cantidad, precio_unitario, descuento, exento",
        "Flag origen=externo → bloquea reenvío SII, anulación, NC posterior (a menos que se decida explícito)",
        "Permitir adjuntar PDF original opcional",
        "Cliente inexistente → crear stub + marcar pendiente",
        "NO descontar stock por estos DTE históricos"
      ]
    }
  ]
}