{
  "lists": [
    "Ideas",
    "Feature requests",
    "Bugs",
    "Client feedback",
    "In progress",
    "In review",
    "Friendly Beta 0.1",
    "Live Beta 0.2",
    "Live 1.0"
  ],
  "labels": {
    "Wave 1": "red",
    "Wave 2": "orange",
    "Tier A": "yellow",
    "DTE/SII": "green",
    "Design System": "purple",
    "Core": "blue",
    "Roadmap": "sky",
    "Bug": "pink",
    "Blocked": "black",
    "Goal: SaaS-ready": "lime",
    "Goal: UX Polish": "null",
    "Goal: Performance": "null",
    "Goal: Operations": "null",
    "Goal: Docs": "null",
    "Size:S": "green",
    "Size:M": "yellow",
    "Size:L": "orange",
    "Size:XL": "red"
  },
  "cards": [
    {
      "list": "In review",
      "name": "[Modulos P1.4] Wire require_modulo a routers de ventas DTE",
      "labels": [
        "Core",
        "Goal: SaaS-ready",
        "Size:L"
      ],
      "desc": "**Resumen** — Agregar validación de módulos habilitados en routers de ventas (boletas, facturas, guías, etc.) para restringir acceso según suscripción.\n\n**Cambios / Decisiones** — Se aplicó `Depends(require_modulo(...))` a los routers en `backend/app/api/` correspondientes a boletas, facturas, guias_despacho, nota_ventas, cotizaciones y sus variantes adjuntas. Se agregó archivo `backend/tests/test_modulo_gating_ventas.py` con tests integrales que validan acceso 403 cuando no hay módulo y normal cuando sí. Se ajustaron fixtures en `conftest.py` para facilitar pruebas. Se corrigió inclusión del middleware en rutas de emisión en `dte.py`.",
      "checklist": [
        "POST a /api/boletas/ sin módulo 'boletas' → verificar 403",
        "POST a /api/facturas/ con módulo 'facturas' activo → verificar 200",
        "GET a /api/guias_despacho/ sin módulo → verificar 403",
        "POST a /api/cotizaciones/ sin módulo 'cotizaciones' → verificar 403",
        "POST a /api/notas_venta/ con módulo activo → verificar éxito",
        "Verificar audit_log registra intentos fallidos",
        "Ejecutar tests en backend/tests/test_modulo_gating_ventas.py"
      ]
    }
  ]
}
